CHANGES.txt
LICENSE
MANIFEST.in
README.rst
setup.py
src/celery_redis_prometheus/__init__.py
src/celery_redis_prometheus/exporter.py
src/celery_redis_prometheus.egg-info/PKG-INFO
src/celery_redis_prometheus.egg-info/SOURCES.txt
src/celery_redis_prometheus.egg-info/dependency_links.txt
src/celery_redis_prometheus.egg-info/entry_points.txt
src/celery_redis_prometheus.egg-info/not-zip-safe
src/celery_redis_prometheus.egg-info/requires.txt
src/celery_redis_prometheus.egg-info/top_level.txt
src/celery_redis_prometheus/tests/__init__.py
src/celery_redis_prometheus/tests/conftest.py
src/celery_redis_prometheus/tests/test_exporter.py