Metadata-Version: 2.1
Name: celery-redis-prometheus
Version: 1.5.1
Summary: Exports task execution metrics in Prometheus format
Home-page: https://github.com/zeitonline/celery_redis_prometheus
Author: Zeit Online
Author-email: zon-backend@zeit.de
License: BSD
License-File: LICENSE
Requires-Dist: celery>=5.0.0.dev0
Requires-Dist: click
Requires-Dist: prometheus_client
Requires-Dist: setuptools
Provides-Extra: test
Requires-Dist: pytest; extra == "test"
